project_sync-0.2.0.dist-info/DESCRIPTION.rst
project_sync-0.2.0.dist-info/METADATA
project_sync-0.2.0.dist-info/RECORD
project_sync-0.2.0.dist-info/WHEEL
project_sync-0.2.0.dist-info/entry_points.txt
project_sync-0.2.0.dist-info/metadata.json
project_sync-0.2.0.dist-info/top_level.txt
psync/__init__.py
psync/cli.py
psync/psync.py
psync/watcher.py
