Metadata-Version: 2.0
Name: project-sync
Version: 0.2.0
Summary: A simple tool for synchronizing local project (files) to remote server.
Home-page: https://github.com/lazywei/psync
Author: Chih-Wei Chang
Author-email: bert.cwchang@gmail.com
License: MIT license
Keywords: project sync rsync auto watch
Platform: UNKNOWN
Classifier: Development Status :: 3 - Alpha
Classifier: Intended Audience :: Developers
Classifier: License :: OSI Approved :: MIT License
Classifier: Programming Language :: Python :: 2
Classifier: Programming Language :: Python :: 2.7
Classifier: Programming Language :: Python :: 3
Classifier: Programming Language :: Python :: 3.3
Classifier: Programming Language :: Python :: 3.4
Classifier: Programming Language :: Python :: 3.5
Classifier: Programming Language :: Python :: 3.6
Requires-Dist: Click (>=6.0)
Requires-Dist: PyYAML (>=3.12)
Requires-Dist: watchdog (>=0.8.3)
